cap1xxx.py
Cap1xxx-0.1.4.dist-info/LICENSE.txt
Cap1xxx-0.1.4.dist-info/METADATA
Cap1xxx-0.1.4.dist-info/WHEEL
Cap1xxx-0.1.4.dist-info/top_level.txt
Cap1xxx-0.1.4.dist-info/RECORD
